am3/__init__.py
am3/alias.py
am3/am.py
am3/api.py
am3/cmdline.py
am3/settings.py
am3/version.py
am3/cli/__init__.py
am3/cli/alias_commands.py
am3/cli/commands.py
am3/config/__init__.py
am3/config/manager.py
am3/core/__init__.py
am3/core/app_manager.py
am3/process/__init__.py
am3/process/process_manager.py
am3/startup_scripts/launchd.tpl
am3/startup_scripts/systemd.tpl
am3/utils/__init__.py
am3/utils/cmd_util.py
am3/utils/color_util.py
am3/utils/linux_util.py
am3/utils/path_util.py
am3/utils/process_util.py
am3-1.1.1.dist-info/licenses/LICENSE.txt
am3-1.1.1.dist-info/METADATA
am3-1.1.1.dist-info/WHEEL
am3-1.1.1.dist-info/entry_points.txt
am3-1.1.1.dist-info/top_level.txt
am3-1.1.1.dist-info/RECORD
