Metadata-Version: 2.4
Name: am3
Version: 1.1.1
Summary: Application Manager written with python 3
Home-page: https://github.com/nriver/am3
Author: Nriver
Author-email: 
Project-URL: Bug Reports, https://github.com/nriver/am3/issues
Project-URL: Funding, https://github.com/nriver/am3
Project-URL: Say Thanks!, https://github.com/nriver/am3
Project-URL: Source, https://github.com/nriver/am3/
Keywords: application manger,process manager
Classifier: Development Status :: 5 - Production/Stable
Classifier: Intended Audience :: Developers
Classifier: Topic :: System :: Systems Administration
Classifier: License :: OSI Approved :: GNU Affero General Public License v3
Classifier: Programming Language :: Python :: 3
Classifier: Programming Language :: Python :: 3.9
Classifier: Programming Language :: Python :: 3.10
Classifier: Programming Language :: Python :: 3.11
Classifier: Programming Language :: Python :: 3.12
Classifier: Programming Language :: Python :: 3.13
Classifier: Programming Language :: Python :: 3 :: Only
Requires-Python: >=3.6, <4
License-File: LICENSE.txt
Requires-Dist: loguru>=0.5.0
Requires-Dist: flask>=2.0.0
Requires-Dist: psutil>=5.7.0
Requires-Dist: PrettyTable>=2.0.0
Requires-Dist: python-socketio>=5.14.0
Requires-Dist: websockets>=12.0
Requires-Dist: watchdog>=2.0.0
Requires-Dist: click>=7.0
Dynamic: author
Dynamic: classifier
Dynamic: description
Dynamic: description-content-type
Dynamic: home-page
Dynamic: keywords
Dynamic: license-file
Dynamic: project-url
Dynamic: requires-dist
Dynamic: requires-python
Dynamic: summary
